rcbtools/__init__.py
rcbtools/observed_abund.csv
rcbtools-0.4.0.dist-info/LICENSE
rcbtools-0.4.0.dist-info/METADATA
rcbtools-0.4.0.dist-info/WHEEL
rcbtools-0.4.0.dist-info/top_level.txt
rcbtools-0.4.0.dist-info/RECORD
