Metadata-Version: 2.1
Name: rcbtools
Version: 0.4.0
Summary: Analysis toolkit for RCB stars evolved in MESA
Home-page: https://github.com/bamunson/rcbtools
Author: Brad Munson
Author-email: brad.munson94@gmail.com
License: MIT
Platform: UNKNOWN
Requires-Dist: numpy
Requires-Dist: matplotlib
Requires-Dist: pandas
